ou_container_content/__init__.py
ou_container_content/__main__.py
ou_container_content/distributor.py
ou_container_content/frontend/__init__.py
ou_container_content/frontend/build/__init__.py
ou_container_content/frontend/build/bundle.css
ou_container_content/frontend/build/bundle.js
ou_container_content/frontend/build/bundle.js.map
ou_container_content/frontend/global.css
ou_container_content/frontend/index.html
ou_container_content/frontend/ou-favicon-1.png
ou_container_content/frontend/ou-favicon-2.png
ou_container_content/frontend/ou-favicon-3.png
ou_container_content/frontend/ou-favicon-4.png
ou_container_content/handlers.py
ou_container_content/process.py
ou_container_content/scripts.py
ou_container_content/services.py
ou_container_content/validator.py
ou_container_content-1.2.0.dist-info/METADATA
ou_container_content-1.2.0.dist-info/WHEEL
ou_container_content-1.2.0.dist-info/entry_points.txt
ou_container_content-1.2.0.dist-info/RECORD
