Metadata-Version: 2.1
Name: ou-container-content
Version: 1.2.0
Summary: 
Author: Mark Hall
Author-email: mark.hall@open.ac.uk
Requires-Python: >=3.7,<4.0
Classifier: Programming Language :: Python :: 3
Classifier: Programming Language :: Python :: 3.7
Classifier: Programming Language :: Python :: 3.8
Classifier: Programming Language :: Python :: 3.9
Classifier: Programming Language :: Python :: 3.10
Classifier: Programming Language :: Python :: 3.11
Requires-Dist: Cerberus (>=1.3.3,<2.0.0)
Requires-Dist: PyYAML (>=6.0.0,<7.0.0)
Requires-Dist: click (>=8.1.3,<9.0.0)
Requires-Dist: tornado (>=6.1,<7.0)
